gitlab_registry_usage/__init__.py
gitlab_registry_usage/__main__.py
gitlab_registry_usage/_version.py
gitlab_registry_usage/cli.py
gitlab_registry_usage/registry/__init__.py
gitlab_registry_usage/registry/high_level_api.py
gitlab_registry_usage/registry/low_level_api.py
gitlab_registry_usage-0.3.3.dist-info/LICENSE
gitlab_registry_usage-0.3.3.dist-info/METADATA
gitlab_registry_usage-0.3.3.dist-info/WHEEL
gitlab_registry_usage-0.3.3.dist-info/entry_points.txt
gitlab_registry_usage-0.3.3.dist-info/top_level.txt
gitlab_registry_usage-0.3.3.dist-info/RECORD
