Metadata-Version: 2.1
Name: gitlab-registry-usage
Version: 0.3.3
Summary: This is a package for querying the size of repositories in a GitLab registry.
Home-page: https://github.com/sciapp/gitlab-registry-usage
Author: Ingo Meyer
Author-email: i.meyer@fz-juelich.de
License: MIT
Keywords: Git,GitLab,Docker,Registry,disk capacity
Classifier: Development Status :: 4 - Beta
Classifier: Environment :: Console
Classifier: Intended Audience :: System Administrators
Classifier: License :: OSI Approved :: MIT License
Classifier: Programming Language :: Python :: 3
Classifier: Programming Language :: Python :: 3.5
Classifier: Programming Language :: Python :: 3.6
Classifier: Programming Language :: Python :: 3.7
Classifier: Programming Language :: Python :: 3.8
Classifier: Programming Language :: Python :: 3.9
Classifier: Programming Language :: Python :: 3 :: Only
Classifier: Topic :: Software Development :: Version Control :: Git
Classifier: Topic :: System :: Systems Administration
Requires-Python: ~=3.5
License-File: LICENSE
Requires-Dist: pyOpenSSL
Requires-Dist: requests
Requires-Dist: yacl
